caching/__init__.py
caching/cache.py
caching/storage.py
caching-0.1.dev8.dist-info/DESCRIPTION.rst
caching-0.1.dev8.dist-info/METADATA
caching-0.1.dev8.dist-info/RECORD
caching-0.1.dev8.dist-info/WHEEL
caching-0.1.dev8.dist-info/metadata.json
caching-0.1.dev8.dist-info/top_level.txt
