Metadata-Version: 1.1
Name: caching
Version: 0.1.dev8
Summary: Python utils and decorators for cаching with TTL, maxsize and file-based storage.
Home-page: https://github.com/bofm/python-caching
Author: bofm
Author-email: bofm@github.com
License: UNKNOWN
Download-URL: https://github.com/bofm/python-caching/tarball/0.1.dev8
Keywords: cache,caching
Platform: UNKNOWN
Classifier: Development Status :: 4 - Beta
Classifier: Intended Audience :: Developers
Classifier: License :: OSI Approved :: MIT License
Classifier: Natural Language :: English
Classifier: Programming Language :: Python :: 3.6
Classifier: Programming Language :: Python :: Implementation :: CPython
Classifier: Programming Language :: Python :: Implementation :: PyPy
